ImageThief/__init__.py
ImageThief/_endpointProcessor.py
ImageThief/_fileDecoder.py
ImageThief/_globalDict.py
ImageThief/_thief.py
ImageThief-2.0.3.dist-info/METADATA
ImageThief-2.0.3.dist-info/WHEEL
ImageThief-2.0.3.dist-info/top_level.txt
ImageThief-2.0.3.dist-info/RECORD
