Metadata-Version: 2.1
Name: ImageThief
Version: 2.0.3
Summary: Get files from server running on default route
Home-page: UNKNOWN
Author: Dhanush
Author-email: dhanushdazz@gmail.com
License: UNKNOWN
Keywords: raspberrypi,image-processing,image-getter
Platform: UNKNOWN
Classifier: Programming Language :: Python :: 3
Classifier: Operating System :: OS Independent
Requires-Dist: flask
Requires-Dist: requests
